resvg_py-0.2.5.dist-info/METADATA
resvg_py-0.2.5.dist-info/WHEEL
resvg_py-0.2.5.dist-info/licenses/LICENSE
resvg_py.libs/libgcc_s-262c4f60.so.1
resvg_py/__init__.py
resvg_py/__init__.pyi
resvg_py/py.typed
resvg_py/resvg_py.pypy311-pp73-arm-linux-gnu.so
resvg_py-0.2.5.dist-info/RECORD
