Metadata-Version: 2.4
Name: resvg_py
Version: 0.2.5
Classifier: Programming Language :: Rust
Classifier: Programming Language :: Python :: Implementation :: CPython
Classifier: Programming Language :: Python :: Implementation :: PyPy
License-File: LICENSE
Author-email: baseplate-admin <61817579+baseplate-admin@users.noreply.github.com>
Requires-Python: >=3.9
Project-URL: Source Code, https://github.com/baseplate-admin/resvg-py
Project-URL: Issues, https://github.com/baseplate-admin/resvg-py/issues
Project-URL: Documentation, https://resvg-py.readthedocs.io/
